qultra/__init__.py
qultra/constants.py
qultra/core.py
qultra/find_zeros.py
qultra-0.1.1.dist-info/licenses/LICENSE
qultra-0.1.1.dist-info/METADATA
qultra-0.1.1.dist-info/WHEEL
qultra-0.1.1.dist-info/top_level.txt
qultra-0.1.1.dist-info/RECORD
