Metadata-Version: 2.4
Name: qultra
Version: 0.1.1
Summary: Quantum Lumped and Transmission Resonator Analyzer
Author-email: Simona Zaccaria <simona.zaccaria4@unibo.it>, Antonio Gnudi <antonio.gnudi@unibo.it>
License: MIT License
Requires-Python: >=3.10
License-File: LICENSE
Requires-Dist: numpy
Requires-Dist: scipy>=1.15.2
Requires-Dist: tabulate
Requires-Dist: mpmath>=1.3.0
Dynamic: license-file
